<?xml version="1.0" encoding="UTF-8"?>
<xwikidoc>
<web>XWiki</web>
<name>XWikiGroupSheet</name>
<language></language>
<defaultLanguage>en</defaultLanguage>
<translation>0</translation>
<parent>XWiki.XWikiGroups</parent>
<creator>XWiki.Admin</creator>
<author>XWiki.Admin</author>
<customClass></customClass>
<contentAuthor>XWiki.Admin</contentAuthor>
<creationDate>1242173909000</creationDate>
<date>1242173909000</date>
<contentUpdateDate>1242173909000</contentUpdateDate>
<version>1.1</version>
<title></title>
<template></template>
<defaultTemplate></defaultTemplate>
<validationScript></validationScript>
<comment></comment>
<minorEdit>false</minorEdit>
<syntaxId>xwiki/1.0</syntaxId>
<hidden>false</hidden>
<content>#set($mainwk = $xcontext.isMainWiki())
$xwiki.jsfx.use("js/xwiki/usersandgroups/usersandgroups.js", true)
$xwiki.ssfx.use("js/xwiki/usersandgroups/usersandgroups.css")
$xwiki.jsfx.use("js/xwiki/table/livetable.js", true)
$xwiki.ssfx.use("js/xwiki/table/livetable.css", true)
#set($groupDoc = $doc)
#if($doc.fullName == 'Main.UserDirectory')
  #set($groupDoc = $xwiki.getDocument('XWiki.XWikiAllGroup'))
#end
#macro(hasEditGroupRight)
  #set($hasEditGroupRight = false)
  #if($hasAdmin &amp;&amp; $doc.getObject('XWiki.XWikiGroups', false))
    #set($hasEditGroupRight = true)
  #end
#end
#hasEditGroupRight()
##
##
#if($xcontext.action == 'inline' &amp;&amp; $hasEditGroupRight)
  &lt;div id="addNewMember"&gt;
    &lt;table&gt;
      &lt;tr&gt;
        &lt;td class="addlabel"&gt;$msg.get("xe.admin.groups.addUser")
          #if(!$mainwk)
            &lt;/td&gt;
            &lt;td&gt;&lt;select name="wiki" onchange="changeWiki(this);"&gt;
                &lt;option value="local" selected="selected"&gt;$msg.get("xe.admin.local")&lt;/option&gt;
                &lt;option value="global"&gt;$msg.get("xe.admin.global")&lt;/option&gt;
              &lt;/select&gt;
            &lt;/td&gt;
          #else
            &lt;input type="hidden" name="wiki" value="local" /&gt;&lt;/td&gt;
          #end
        &lt;td&gt;
          &lt;input id="userSuggest" type="text" size="30" name="newMember" autocomplete="off" /&gt;
        &lt;/td&gt;
        &lt;td&gt;
          &lt;input type="button" id="addNewUser" class="button" value="$msg.get('xe.admin.groups.addUser.submit')" /&gt;
        &lt;/td&gt;
      &lt;/tr&gt;
      &lt;tr&gt;
        &lt;td class="addlabel"&gt;$msg.get("xe.admin.groups.addGroup")
          #if(!$mainwk)
            &lt;/td&gt;
            &lt;td&gt;&lt;select name="wiki" onchange="changeWiki(this);"&gt;
                &lt;option value="local" selected="selected"&gt;$msg.get("xe.admin.local")&lt;/option&gt;
                &lt;option value="global"&gt;$msg.get("xe.admin.global")&lt;/option&gt;
              &lt;/select&gt;
            &lt;/td&gt;
          #else
            &lt;input type="hidden" name="wiki" value="local" /&gt;&lt;/td&gt;
          #end
        &lt;td&gt;
          &lt;input id="groupSuggest" type="text" size="30" name="newMember" autocomplete="off" /&gt;
        &lt;/td&gt;
        &lt;td&gt;
          &lt;input type="button" id="addNewGroup" class="button" value="$msg.get('xe.admin.groups.addGroup.submit')" /&gt;
        &lt;/td&gt;
      &lt;/tr&gt;
      &lt;tr&gt;&lt;td colspan="3" id="errMsg"&gt;&lt;/td&gt;&lt;/tr&gt;
    &lt;/table&gt;
  &lt;/div&gt;&lt;br /&gt;
  ##
  ##
  {pre}
  &lt;script type="text/javascript"&gt;
    // &lt;![CDATA[
      if (typeof XWiki == "undefined") {
        var XWiki = {}; 
      }
      Object.extend(XWiki, {
        groupmanager : {
          /*
          ** Initialize Group Manager javascript widgets (called on document load).
          */
          userSuggest: null, 
      
          groupSuggest: null,
      
          init: function() {
            if (XWiki.contextaction != 'view') {
              this.initSuggestWidget();
              this.initAddNewMemberWidget();
            }
          },
          initSuggestWidget: function() {
            if($('userSuggest')){
              $('userSuggest').observe('focus', this.createSuggest.bind(this, $('userSuggest'), 'user', true));
            }
            if($('groupSuggest')){
              $('groupSuggest').observe('focus', this.createSuggest.bind(this, $('groupSuggest'), 'group', false));
            }
          },
          initAddNewMemberWidget: function() {
            if($('addNewUser')){
              $('addNewUser').observe('click', this.addNewMember.bind(this, 'user', $('userSuggest')));
            }
            if($('addNewGroup')){
              $('addNewGroup').observe('click', this.addNewMember.bind(this, 'group', $('groupSuggest')));
            }
          }, 
          createSuggest: function(input, uorg, suggestObj) {
            //clear the errors
            $('errMsg').innerHTML = "";
             suggesturl = "${doc.getURL()}?xpage=uorgsuggest&amp;classname=XWiki.XWikiUsers&amp;wiki=local";

            //if(suggesturl.indexOf("&amp;" + "uorg=") &gt; 0) 
            //  suggesturl = suggesturl.substring(0, suggesturl.indexOf("&amp;" + "uorg="));
            if(uorg == "user"){
              suggesturl += "&amp;" + "uorg=user" + "&amp;";
            }else{
              suggesturl += "&amp;" + "uorg=group" + "&amp;";
            }
            // input.id = input.id;
            return new ajaxSuggest(input, { script: suggesturl, varname:'input' } );
          },
          addNewMember: function(uorg, input) {
            if(input) {
              var url = "${doc.getURL()}?xpage=adduorg" + "&amp;" + "uorg=" + uorg + "&amp;" + "name=" + input.value;
              new Ajax.Request(url, {
                method: 'get',
                onSuccess: function(transport) {
                  $('userSuggest').value = "";
                  $('groupSuggest').value = "";
                  var nr = parseInt(transport.responseText);
                  if(nr == 0){
                    if(uorg == "user"){
                      $('errMsg').innerHTML = "$msg.get('xe.admin.groups.addUser.duplicate')";
                    }else{
                      $('errMsg').innerHTML = "$msg.get('xe.admin.groups.addGroup.duplicate')";
                    }
                  }else{
                    var end = editgrouptable.limit;
                    var start = editgrouptable.lastOffset;
                    editgrouptable.clearCache();
                    if(start &lt; 1)  
                      start = 1;
                    editgrouptable.getRows(start, end, start, end);
                  }
                }
              });
            }
          }
        }
      });
      XWiki.groupmanager.init();        
    // ]]&gt;
  &lt;/script&gt;
  {/pre}
#end
#set($columnOptions = {
  "member" : {'link': 'auto', 'type': 'text'},
  '_avatar' : { 'type' : 'none', 'link' : 'none', 'html' : 'true', 'sortable' : false },
  "_actions" : {
    'actions': ['delete'],
    'actionCallbacks': {'delete': 'table.deleteRow(i);'},
    'ajaxActions': {'delete': true}
   }
})
#if($hasAdmin &amp;&amp; $xcontext.action == 'inline' &amp;&amp; $hasEditGroupRight)
  #set($columns = ['_avatar', 'member', '_actions'])
#else
  #set($columns = ['_avatar', 'member'])
#end
#livetable("groupusers", $columns, $columnOptions, {'url' : "${groupDoc.getURL()}?xpage=getgroupmembers", 'translationPrefix' : 'xe.admin.groups.', 'javascriptName' : 'editgrouptable'})
</content></xwikidoc>
