<?xml version="1.1" encoding="UTF-8"?>

<!--
 * See the NOTICE file distributed with this work for additional
 * information regarding copyright ownership.
 *
 * This is free software; you can redistribute it and/or modify it
 * under the terms of the GNU Lesser General Public License as
 * published by the Free Software Foundation; either version 2.1 of
 * the License, or (at your option) any later version.
 *
 * This software is distributed in the hope that it will be useful,
 * but WITHOUT ANY WARRANTY; without even the implied warranty of
 * MERCHANTABILITY or FITNESS FOR A PARTICULAR PURPOSE. See the GNU
 * Lesser General Public License for more details.
 *
 * You should have received a copy of the GNU Lesser General Public
 * License along with this software; if not, write to the Free
 * Software Foundation, Inc., 51 Franklin St, Fifth Floor, Boston, MA
 * 02110-1301 USA, or see the FSF site: http://www.fsf.org.
-->

<xwikidoc version="1.3" reference="Scheduler.NotificationEmailHourlySender" locale="">
  <web>Scheduler</web>
  <name>NotificationEmailHourlySender</name>
  <language/>
  <defaultLanguage/>
  <translation>0</translation>
  <creator>xwiki:XWiki.Admin</creator>
  <creationDate>1497368950000</creationDate>
  <parent>Scheduler.WebHome</parent>
  <author>xwiki:XWiki.Admin</author>
  <contentAuthor>xwiki:XWiki.Admin</contentAuthor>
  <date>1497369134000</date>
  <contentUpdateDate>1497368950000</contentUpdateDate>
  <version>1.1</version>
  <title>Notification Email Hourly Sender</title>
  <comment/>
  <minorEdit>false</minorEdit>
  <syntaxId>xwiki/2.1</syntaxId>
  <hidden>true</hidden>
  <content/>
  <object>
    <name>Scheduler.NotificationEmailHourlySender</name>
    <number>0</number>
    <className>XWiki.Notifications.Code.EmailJobClass</className>
    <guid>1d90d96f-188d-4495-b758-f96974274450</guid>
    <class>
      <name>XWiki.Notifications.Code.EmailJobClass</name>
      <customClass/>
      <customMapping/>
      <defaultViewSheet/>
      <defaultEditSheet/>
      <defaultWeb/>
      <nameField/>
      <validationScript/>
      <lastFireTime>
        <customDisplay/>
        <dateFormat>dd/MM/yyyy HH:mm:ss</dateFormat>
        <disabled>0</disabled>
        <emptyIsToday>1</emptyIsToday>
        <name>lastFireTime</name>
        <number>1</number>
        <picker>1</picker>
        <prettyName>Last notifier fire time</prettyName>
        <size>20</size>
        <unmodifiable>0</unmodifiable>
        <validationMessage/>
        <validationRegExp/>
        <classType>com.xpn.xwiki.objects.classes.DateClass</classType>
      </lastFireTime>
    </class>
    <property>
      <lastFireTime>2017-06-13 14:29:31.991</lastFireTime>
    </property>
  </object>
  <object>
    <name>Scheduler.NotificationEmailHourlySender</name>
    <number>0</number>
    <className>XWiki.SchedulerJobClass</className>
    <guid>23498043-bfbb-4cc1-8002-1f467ff209a8</guid>
    <class>
      <name>XWiki.SchedulerJobClass</name>
      <customClass/>
      <customMapping/>
      <defaultViewSheet/>
      <defaultEditSheet/>
      <defaultWeb/>
      <nameField/>
      <validationScript/>
      <contextDatabase>
        <disabled>0</disabled>
        <name>contextDatabase</name>
        <number>9</number>
        <prettyName>Job execution context database</prettyName>
        <size>30</size>
        <unmodifiable>0</unmodifiable>
        <classType>com.xpn.xwiki.objects.classes.StringClass</classType>
      </contextDatabase>
      <contextLang>
        <disabled>0</disabled>
        <name>contextLang</name>
        <number>8</number>
        <prettyName>Job execution context lang</prettyName>
        <size>30</size>
        <unmodifiable>0</unmodifiable>
        <classType>com.xpn.xwiki.objects.classes.StringClass</classType>
      </contextLang>
      <contextUser>
        <disabled>0</disabled>
        <name>contextUser</name>
        <number>7</number>
        <prettyName>Job execution context user</prettyName>
        <size>30</size>
        <unmodifiable>0</unmodifiable>
        <classType>com.xpn.xwiki.objects.classes.StringClass</classType>
      </contextUser>
      <cron>
        <disabled>0</disabled>
        <name>cron</name>
        <number>5</number>
        <prettyName>Cron Expression</prettyName>
        <size>30</size>
        <unmodifiable>0</unmodifiable>
        <classType>com.xpn.xwiki.objects.classes.StringClass</classType>
      </cron>
      <jobClass>
        <disabled>0</disabled>
        <name>jobClass</name>
        <number>3</number>
        <prettyName>Job Class</prettyName>
        <size>60</size>
        <unmodifiable>0</unmodifiable>
        <classType>com.xpn.xwiki.objects.classes.StringClass</classType>
      </jobClass>
      <jobDescription>
        <disabled>0</disabled>
        <name>jobDescription</name>
        <number>2</number>
        <prettyName>Job Description</prettyName>
        <rows>10</rows>
        <size>45</size>
        <unmodifiable>0</unmodifiable>
        <classType>com.xpn.xwiki.objects.classes.TextAreaClass</classType>
      </jobDescription>
      <jobName>
        <disabled>0</disabled>
        <name>jobName</name>
        <number>1</number>
        <prettyName>Job Name</prettyName>
        <size>60</size>
        <unmodifiable>0</unmodifiable>
        <classType>com.xpn.xwiki.objects.classes.StringClass</classType>
      </jobName>
      <script>
        <contenttype>PureText</contenttype>
        <disabled>0</disabled>
        <editor>PureText</editor>
        <name>script</name>
        <number>6</number>
        <prettyName>Job Script</prettyName>
        <rows>10</rows>
        <size>60</size>
        <unmodifiable>0</unmodifiable>
        <classType>com.xpn.xwiki.objects.classes.TextAreaClass</classType>
      </script>
      <status>
        <disabled>0</disabled>
        <name>status</name>
        <number>4</number>
        <prettyName>Status</prettyName>
        <size>30</size>
        <unmodifiable>0</unmodifiable>
        <classType>com.xpn.xwiki.objects.classes.StringClass</classType>
      </status>
    </class>
    <property>
      <contextDatabase>xwiki</contextDatabase>
    </property>
    <property>
      <contextLang>en</contextLang>
    </property>
    <property>
      <contextUser>XWiki.superadmin</contextUser>
    </property>
    <property>
      <cron>0 0 * * * ?</cron>
    </property>
    <property>
      <jobClass>org.xwiki.notifications.notifiers.internal.email.NotificationEmailJob</jobClass>
    </property>
    <property>
      <jobDescription> </jobDescription>
    </property>
    <property>
      <jobName>Notifications hourly email</jobName>
    </property>
    <property>
      <script/>
    </property>
    <property>
      <status>Normal</status>
    </property>
  </object>
  <object>
    <name>Scheduler.NotificationEmailHourlySender</name>
    <number>0</number>
    <className>XWiki.XWikiRights</className>
    <guid>ade9488a-aa52-477a-9203-05083e68aca2</guid>
    <class>
      <name>XWiki.XWikiRights</name>
      <customClass/>
      <customMapping/>
      <defaultViewSheet/>
      <defaultEditSheet/>
      <defaultWeb/>
      <nameField/>
      <validationScript/>
      <allow>
        <defaultValue>1</defaultValue>
        <disabled>0</disabled>
        <displayFormType>select</displayFormType>
        <displayType>allow</displayType>
        <name>allow</name>
        <number>4</number>
        <prettyName>Allow/Deny</prettyName>
        <unmodifiable>0</unmodifiable>
        <classType>com.xpn.xwiki.objects.classes.BooleanClass</classType>
      </allow>
      <groups>
        <cache>0</cache>
        <disabled>0</disabled>
        <displayType>input</displayType>
        <multiSelect>1</multiSelect>
        <name>groups</name>
        <number>1</number>
        <picker>1</picker>
        <prettyName>Groups</prettyName>
        <relationalStorage>0</relationalStorage>
        <separator> </separator>
        <size>5</size>
        <unmodifiable>0</unmodifiable>
        <classType>com.xpn.xwiki.objects.classes.GroupsClass</classType>
      </groups>
      <levels>
        <cache>0</cache>
        <disabled>0</disabled>
        <displayType>select</displayType>
        <multiSelect>1</multiSelect>
        <name>levels</name>
        <number>2</number>
        <prettyName>Levels</prettyName>
        <relationalStorage>0</relationalStorage>
        <separator> </separator>
        <size>3</size>
        <unmodifiable>0</unmodifiable>
        <classType>com.xpn.xwiki.objects.classes.LevelsClass</classType>
      </levels>
      <users>
        <cache>0</cache>
        <disabled>0</disabled>
        <displayType>input</displayType>
        <multiSelect>1</multiSelect>
        <name>users</name>
        <number>3</number>
        <picker>1</picker>
        <prettyName>Users</prettyName>
        <relationalStorage>0</relationalStorage>
        <separator> </separator>
        <size>5</size>
        <unmodifiable>0</unmodifiable>
        <classType>com.xpn.xwiki.objects.classes.UsersClass</classType>
      </users>
    </class>
    <property>
      <allow>1</allow>
    </property>
    <property>
      <groups/>
    </property>
    <property>
      <levels>edit,delete</levels>
    </property>
    <property>
      <users/>
    </property>
  </object>
  <object>
    <name>Scheduler.NotificationEmailHourlySender</name>
    <number>1</number>
    <className>XWiki.XWikiRights</className>
    <guid>22351a4d-0e3e-47c0-a64d-4064ca6d1514</guid>
    <class>
      <name>XWiki.XWikiRights</name>
      <customClass/>
      <customMapping/>
      <defaultViewSheet/>
      <defaultEditSheet/>
      <defaultWeb/>
      <nameField/>
      <validationScript/>
      <allow>
        <defaultValue>1</defaultValue>
        <disabled>0</disabled>
        <displayFormType>select</displayFormType>
        <displayType>allow</displayType>
        <name>allow</name>
        <number>4</number>
        <prettyName>Allow/Deny</prettyName>
        <unmodifiable>0</unmodifiable>
        <classType>com.xpn.xwiki.objects.classes.BooleanClass</classType>
      </allow>
      <groups>
        <cache>0</cache>
        <disabled>0</disabled>
        <displayType>input</displayType>
        <multiSelect>1</multiSelect>
        <name>groups</name>
        <number>1</number>
        <picker>1</picker>
        <prettyName>Groups</prettyName>
        <relationalStorage>0</relationalStorage>
        <separator> </separator>
        <size>5</size>
        <unmodifiable>0</unmodifiable>
        <classType>com.xpn.xwiki.objects.classes.GroupsClass</classType>
      </groups>
      <levels>
        <cache>0</cache>
        <disabled>0</disabled>
        <displayType>select</displayType>
        <multiSelect>1</multiSelect>
        <name>levels</name>
        <number>2</number>
        <prettyName>Levels</prettyName>
        <relationalStorage>0</relationalStorage>
        <separator> </separator>
        <size>3</size>
        <unmodifiable>0</unmodifiable>
        <classType>com.xpn.xwiki.objects.classes.LevelsClass</classType>
      </levels>
      <users>
        <cache>0</cache>
        <disabled>0</disabled>
        <displayType>input</displayType>
        <multiSelect>1</multiSelect>
        <name>users</name>
        <number>3</number>
        <picker>1</picker>
        <prettyName>Users</prettyName>
        <relationalStorage>0</relationalStorage>
        <separator> </separator>
        <size>5</size>
        <unmodifiable>0</unmodifiable>
        <classType>com.xpn.xwiki.objects.classes.UsersClass</classType>
      </users>
    </class>
    <property>
      <allow>1</allow>
    </property>
    <property>
      <groups/>
    </property>
    <property>
      <levels>view</levels>
    </property>
    <property>
      <users/>
    </property>
  </object>
</xwikidoc>
