<?xml version="1.1" encoding="UTF-8"?>

<!--
 * See the NOTICE file distributed with this work for additional
 * information regarding copyright ownership.
 *
 * This is free software; you can redistribute it and/or modify it
 * under the terms of the GNU Lesser General Public License as
 * published by the Free Software Foundation; either version 2.1 of
 * the License, or (at your option) any later version.
 *
 * This software is distributed in the hope that it will be useful,
 * but WITHOUT ANY WARRANTY; without even the implied warranty of
 * MERCHANTABILITY or FITNESS FOR A PARTICULAR PURPOSE. See the GNU
 * Lesser General Public License for more details.
 *
 * You should have received a copy of the GNU Lesser General Public
 * License along with this software; if not, write to the Free
 * Software Foundation, Inc., 51 Franklin St, Fifth Floor, Boston, MA
 * 02110-1301 USA, or see the FSF site: http://www.fsf.org.
-->

<xwikidoc version="1.6" reference="AnnotationCode.AnnotatePopupInline" locale="">
  <web>AnnotationCode</web>
  <name>AnnotatePopupInline</name>
  <language/>
  <defaultLanguage/>
  <translation>0</translation>
  <creator>xwiki:XWiki.Admin</creator>
  <author>xwiki:XWiki.Admin</author>
  <contentAuthor>xwiki:XWiki.Admin</contentAuthor>
  <parent>AnnotationCode.WebHome</parent>
  <version>1.1</version>
  <title>AnnotatePopupInline</title>
  <comment/>
  <minorEdit>false</minorEdit>
  <syntaxId>xwiki/2.1</syntaxId>
  <hidden>true</hidden>
  <content>Inline popup to annotate by selecting text (user-friendly alternative to the keyboard shortcut)</content>
  <object>
    <name>AnnotationCode.AnnotatePopupInline</name>
    <number>0</number>
    <className>XWiki.JavaScriptExtension</className>
    <guid>d2429a21-dbe2-4dd1-9511-3bc911af965c</guid>
    <class>
      <name>XWiki.JavaScriptExtension</name>
      <customClass/>
      <customMapping/>
      <defaultViewSheet/>
      <defaultEditSheet/>
      <defaultWeb/>
      <nameField/>
      <validationScript/>
      <cache>
        <cache>0</cache>
        <defaultValue>long</defaultValue>
        <disabled>0</disabled>
        <displayType>select</displayType>
        <freeText>forbidden</freeText>
        <largeStorage>0</largeStorage>
        <multiSelect>0</multiSelect>
        <name>cache</name>
        <number>5</number>
        <prettyName>Caching policy</prettyName>
        <relationalStorage>0</relationalStorage>
        <separator> </separator>
        <separators>|, </separators>
        <size>1</size>
        <unmodifiable>0</unmodifiable>
        <values>long|short|default|forbid</values>
        <classType>com.xpn.xwiki.objects.classes.StaticListClass</classType>
      </cache>
      <code>
        <contenttype>PureText</contenttype>
        <disabled>0</disabled>
        <editor>PureText</editor>
        <name>code</name>
        <number>2</number>
        <prettyName>Code</prettyName>
        <restricted>0</restricted>
        <rows>20</rows>
        <size>50</size>
        <unmodifiable>0</unmodifiable>
        <classType>com.xpn.xwiki.objects.classes.TextAreaClass</classType>
      </code>
      <name>
        <disabled>0</disabled>
        <name>name</name>
        <number>1</number>
        <prettyName>Name</prettyName>
        <size>30</size>
        <unmodifiable>0</unmodifiable>
        <classType>com.xpn.xwiki.objects.classes.StringClass</classType>
      </name>
      <parse>
        <disabled>0</disabled>
        <displayFormType>select</displayFormType>
        <displayType>yesno</displayType>
        <name>parse</name>
        <number>4</number>
        <prettyName>Parse content</prettyName>
        <unmodifiable>0</unmodifiable>
        <classType>com.xpn.xwiki.objects.classes.BooleanClass</classType>
      </parse>
      <use>
        <cache>0</cache>
        <disabled>0</disabled>
        <displayType>select</displayType>
        <freeText>forbidden</freeText>
        <largeStorage>0</largeStorage>
        <multiSelect>0</multiSelect>
        <name>use</name>
        <number>3</number>
        <prettyName>Use this extension</prettyName>
        <relationalStorage>0</relationalStorage>
        <separator> </separator>
        <separators>|, </separators>
        <size>1</size>
        <unmodifiable>0</unmodifiable>
        <values>currentPage|onDemand|always</values>
        <classType>com.xpn.xwiki.objects.classes.StaticListClass</classType>
      </use>
    </class>
    <property>
      <cache>long</cache>
    </property>
    <property>
      <code>"use strict";

const Constants = Object.freeze({
  /**
   * The name of the icon rendered in the popup
   * @type {String}
   */
  ANNOTATE_ICON_NAME: "comment",
  /**
   * The keyboard shortcut that needs to be triggered to create an annotation
   * @type {KeyboardEventInit}
   */
  ANNOTATE_SHORTCUT: { ctrlKey: true, keyCode: 77 }, // ShortcutJS still expects the deprecated keyCode property
  /**
   * The translation key for the button title (for accessibility)
   * @type {String}
   */
  ANNOTATE_TRANSLATION_KEY: "action.create.submit.text",
  /**
   * The CSS class that needs to be added to show the popup
   * @type {String}
   */
  POPUP_CLASS_OPEN: "opened",
  /**
   * The element id of the popup
   * @type {String}
   */
  POPUP_ID: "annotation-popup"
});

// Icons API (see: https://extensions.xwiki.org/xwiki/bin/view/Extension/Icon%20Theme%20Application#HJavaScriptAPI)
define("xwiki-annotate-popup/icons", {
  icons: [Constants.ANNOTATE_ICON_NAME]
});

// Translation API (see: https://extensions.xwiki.org/xwiki/bin/view/Extension/Localization/#HFromJavaScript)
define("xwiki-annotate-popup/translation-keys", {
  prefix: "annotations.",
  keys: [Constants.ANNOTATE_TRANSLATION_KEY]
});

define("xwiki-annotate-popup", ["xwiki-icon!xwiki-annotate-popup/icons", "xwiki-l10n!xwiki-annotate-popup/translation-keys"], function(icons, l10n) {
   /**
    * Debounces a function
    * @param {number} delay - Delay time
    * @returns {Function} - Debounced version of func (result not returned)
    */
   function debounce(func, delay) {
      let timeout;
      return function (...args) {
          clearTimeout(timeout);
          timeout = setTimeout(() =&gt; { func.apply(this, args); }, delay);
      };
   }

   // shared module state (single popup instance)
   const state = {
     popup: null,
     popupButton: null,
     currentRect: null,
     previousFocusElem: null
   };

   /**
    * Inserts popup to DOM
    */
   function addPopupToDOM() {
      const popup = document.createElement("div");
      popup.id = Constants.POPUP_ID;
      popup.role = "dialog";
      popup.ariaHidden = true;

      const popupButton = document.createElement("button");
      popupButton.classList.add("btn", "btn-default", "btn-xs");
      popupButton.title = l10n[Constants.ANNOTATE_TRANSLATION_KEY];

      popupButton.appendChild(icons[Constants.ANNOTATE_ICON_NAME].render());
      popup.appendChild(popupButton);
      document.body.appendChild(popup);

      state.popup = popup;
      state.popupButton = popupButton;
   }

   /**
    * Close popup when pressing escape key
    * @param {KeyboardEvent} event
    */
   function onEscapeKey(event) {
     if (event.key !== "Escape") return;

      closePopup();
      document.removeEventListener("keydown", onEscapeKey);

      // restore focus
      if (state.previousFocusElem &amp;&amp; typeof state.previousFocusElem.focus === "function") {
        state.previousFocusElem.focus();
      }
   }

   /**
    * Closes popup when clicking on the page
    * @returns {(event: ClickEvent) =&gt; void} - A debounced click listener
    */
   const onClickAway = debounce((event) =&gt; {
      // Check if the click was within the bounds of the original text selection
      const isClickInsideSelection = state.currentRect.left &lt;= event.clientX &amp;&amp;
                                     event.clientX &lt;= state.currentRect.right &amp;&amp;
                                     state.currentRect.top &lt;= event.clientY &amp;&amp;
                                     event.clientY &lt;= state.currentRect.bottom;

      if (!state.popup.contains(event.target) &amp;&amp; !isClickInsideSelection) {
          closePopup();
          document.removeEventListener("click", onClickAway);
      }
    }, 60);

   const onViewportChange = debounce(() =&gt; {
      const { popupTop, popupLeft } = getPopupPositioning(window.getSelection());
      state.popup.style.top = popupTop;
      state.popup.style.left = popupLeft;
   }, 100);

   /**
    * Close the popup
    */
   function closePopup() {
      state.popup.classList.remove(Constants.POPUP_CLASS_OPEN);
      state.popup.ariaHidden = false;

      // remove event listeners
      document.removeEventListener("keydown", onEscapeKey);
      document.removeEventListener("click", onClickAway);
      window.visualViewport.removeEventListener("resize", onViewportChange);
   };


   /**
    * Get popup positioning (top and left absolute positioning)
    * @return {{popupTop: number, popupLeft: number}} The popup element and popup button
    */
   function getPopupPositioning(selection) {
      // use rect of last last line/element, important for correct positioning in multi-line selections
      const rects = selection.getRangeAt(0).getClientRects();
      if (!rects.length) return;
      state.currentRect = rects[rects.length - 1];

      const top = (state.currentRect.top + window.scrollY - state.popup.offsetHeight - 4) + "px"; // position 4px over selection so that the popup is not "attached" to the element
      const left = (state.currentRect.left + window.scrollX + state.currentRect.width - (state.popup.offsetWidth / 2)) + "px";

      return { popupTop: top, popupLeft: left };
   }

   /**
    * Displays the popup near the selected text range
    * @param {Selection} selection - A selection
    */
   function openPopup(selection) {
      const { popupTop, popupLeft } = getPopupPositioning(selection);
      state.popup.style.top = popupTop;
      state.popup.style.left = popupLeft;

      state.popup.classList.add(Constants.POPUP_CLASS_OPEN);
      state.popup.ariaHidden = false;

      // focus popup button
      state.previousFocusElem = document.activeElement;
      state.popupButton.focus();

      // add event listeners
      document.addEventListener("keydown", onEscapeKey); // close on escape key
      document.addEventListener("click", onClickAway); // close on click away
      window.visualViewport.addEventListener("resize", onViewportChange); // reposition on viewport change
   }

   /**
    * Register event listeners
    * @param {HTMLElement} wikiContent - The XWiki page container
    */
   function registerListeners(wikiContent) {
      // add click listener to button
      state.popupButton.addEventListener("click", () =&gt; {
         closePopup();
         document.dispatchEvent(new KeyboardEvent("keydown", Constants.ANNOTATE_SHORTCUT));
      });

      // allow pressing enter to click button
      state.popupButton.addEventListener("keydown", (e) =&gt; {
        if (e.key !== "Enter") return;

        e.preventDefault();
        state.popupButton.click();
      });

      /**
       * Checks the current selection and opens the popup
       */
      function onSelectionChange() {
         closePopup(); // close on new select

         const selection = window.getSelection();
         if (!selection || selection.rangeCount === 0 | !selection.toString() || !wikiContent.contains(selection.anchorNode)) {
             return;
         }

         openPopup(selection);
      }
      const selectionListener = debounce(onSelectionChange, 800);
      document.addEventListener("selectionchange", selectionListener, { passive: true });

      // Disable annotation popup in edit mode
      wikiContent.on("xwiki:actions:edit", () =&gt; { document.removeEventListener("selectionchange", selectionListener); });
      wikiContent.on("xwiki:actions:view", () =&gt; { document.addEventListener("selectionchange", selectionListener, { passive: true }); });

      state.popup.addEventListener("pointerdown", (event) =&gt; { event.preventDefault(); });  // prevent losing focus (the selection) when clicking on popup edges

      // TODO: disable popup when annotation dialog is open?
   }

   class AnnotatePopup {
      constructor(wikiContent) {
         this.wikiContent = wikiContent;
         this.popup = null;
         this.annotateButton = null;
         this.currentRect = null;
         this.previousFocus = null;

        // bind handlers once so removeEventListener works
        this.handlePointerDown = this.handlePointerDown.bind(this);
        this.handleKeyDown = this.handleKeyDown.bind(this);
        this.onClickAway = debounce(this.onClickAway.bind(this), 60);
        this.onViewportChange = debounce(this.onViewportChange.bind(this), 100);

        this.createPopup();
        this.registerListeners();
      }
   }

   /**
    * Initialize AnnotatePopupInline
    * @param {HTMLElement} wikiContent - The XWiki page container
    */
   function init(wikiContent) {
      const popupInstance = new AnnotatePopup(wikiContent);

      addPopupToDOM();
      registerListeners(wikiContent);
   }

   return init;
});</code>
    </property>
    <property>
      <name>Annotate Popup -- Main JavaScript</name>
    </property>
    <property>
      <parse>0</parse>
    </property>
    <property>
      <use>always</use>
    </property>
  </object>
  <object>
    <name>AnnotationCode.AnnotatePopupInline</name>
    <number>0</number>
    <className>XWiki.StyleSheetExtension</className>
    <guid>67f1f446-114a-4598-ac7d-b44446e9ecf2</guid>
    <class>
      <name>XWiki.StyleSheetExtension</name>
      <customClass/>
      <customMapping/>
      <defaultViewSheet/>
      <defaultEditSheet/>
      <defaultWeb/>
      <nameField/>
      <validationScript/>
      <cache>
        <cache>0</cache>
        <defaultValue>long</defaultValue>
        <disabled>0</disabled>
        <displayType>select</displayType>
        <freeText>forbidden</freeText>
        <largeStorage>0</largeStorage>
        <multiSelect>0</multiSelect>
        <name>cache</name>
        <number>5</number>
        <prettyName>Caching policy</prettyName>
        <relationalStorage>0</relationalStorage>
        <separator> </separator>
        <separators>|, </separators>
        <size>1</size>
        <unmodifiable>0</unmodifiable>
        <values>long|short|default|forbid</values>
        <classType>com.xpn.xwiki.objects.classes.StaticListClass</classType>
      </cache>
      <code>
        <contenttype>PureText</contenttype>
        <disabled>0</disabled>
        <editor>PureText</editor>
        <name>code</name>
        <number>2</number>
        <prettyName>Code</prettyName>
        <restricted>0</restricted>
        <rows>20</rows>
        <size>50</size>
        <unmodifiable>0</unmodifiable>
        <classType>com.xpn.xwiki.objects.classes.TextAreaClass</classType>
      </code>
      <contentType>
        <cache>0</cache>
        <disabled>0</disabled>
        <displayType>select</displayType>
        <freeText>forbidden</freeText>
        <largeStorage>0</largeStorage>
        <multiSelect>0</multiSelect>
        <name>contentType</name>
        <number>6</number>
        <prettyName>Content Type</prettyName>
        <relationalStorage>0</relationalStorage>
        <separator> </separator>
        <separators>|, </separators>
        <size>1</size>
        <unmodifiable>0</unmodifiable>
        <values>CSS|LESS</values>
        <classType>com.xpn.xwiki.objects.classes.StaticListClass</classType>
      </contentType>
      <name>
        <disabled>0</disabled>
        <name>name</name>
        <number>1</number>
        <prettyName>Name</prettyName>
        <size>30</size>
        <unmodifiable>0</unmodifiable>
        <classType>com.xpn.xwiki.objects.classes.StringClass</classType>
      </name>
      <parse>
        <disabled>0</disabled>
        <displayFormType>select</displayFormType>
        <displayType>yesno</displayType>
        <name>parse</name>
        <number>4</number>
        <prettyName>Parse content</prettyName>
        <unmodifiable>0</unmodifiable>
        <classType>com.xpn.xwiki.objects.classes.BooleanClass</classType>
      </parse>
      <use>
        <cache>0</cache>
        <disabled>0</disabled>
        <displayType>select</displayType>
        <freeText>forbidden</freeText>
        <largeStorage>0</largeStorage>
        <multiSelect>0</multiSelect>
        <name>use</name>
        <number>3</number>
        <prettyName>Use this extension</prettyName>
        <relationalStorage>0</relationalStorage>
        <separator> </separator>
        <separators>|, </separators>
        <size>1</size>
        <unmodifiable>0</unmodifiable>
        <values>currentPage|onDemand|always</values>
        <classType>com.xpn.xwiki.objects.classes.StaticListClass</classType>
      </use>
    </class>
    <property>
      <cache>long</cache>
    </property>
    <property>
      <code>#annotation-popup {
   position: absolute;
   background-color: var(--xwiki-page-content-bg);
   padding: 4px;
   border-radius: 4px;
   box-shadow: 0 1.65px 3px var(--btn-default-border);
   display: none; // to prevent event delivery
   visibility: hidden;
   opacity: 0;
   transition: opacity .2s ease-in;
   &amp;.opened {
      display: block;
      visibility: visible;
      opacity: 1;
   }
}</code>
    </property>
    <property>
      <contentType>CSS</contentType>
    </property>
    <property>
      <name>Annotate Popup -- Main Styles</name>
    </property>
    <property>
      <parse>0</parse>
    </property>
    <property>
      <use>always</use>
    </property>
  </object>
  <object>
    <name>AnnotationCode.AnnotatePopupInline</name>
    <number>0</number>
    <className>XWiki.RequiredRightClass</className>
    <guid>e962e367-f97d-4b92-b08f-10489b92a9cc</guid>
    <class>
      <name>XWiki.RequiredRightClass</name>
      <customClass/>
      <customMapping/>
      <defaultViewSheet/>
      <defaultEditSheet/>
      <defaultWeb/>
      <nameField/>
      <validationScript/>
      <level>
        <cache>0</cache>
        <disabled>0</disabled>
        <displayType>select</displayType>
        <freeText>forbidden</freeText>
        <largeStorage>0</largeStorage>
        <multiSelect>0</multiSelect>
        <name>level</name>
        <number>1</number>
        <prettyName>Level</prettyName>
        <relationalStorage>0</relationalStorage>
        <separator> </separator>
        <separators> ,|</separators>
        <size>1</size>
        <unmodifiable>0</unmodifiable>
        <values>edit|script|wiki_admin|programming</values>
        <classType>com.xpn.xwiki.objects.classes.StaticListClass</classType>
      </level>
    </class>
    <property type="String">
      <level>wiki_admin</level>
    </property>
  </object>
</xwikidoc>
